pangea/__init__.py
pangea/_constants.py
pangea/_typing.py
pangea/asyncio/__init__.py
pangea/asyncio/file_uploader.py
pangea/asyncio/request.py
pangea/asyncio/services/__init__.py
pangea/asyncio/services/ai_guard.py
pangea/asyncio/services/audit.py
pangea/asyncio/services/authn.py
pangea/asyncio/services/authz.py
pangea/asyncio/services/base.py
pangea/asyncio/services/embargo.py
pangea/asyncio/services/file_scan.py
pangea/asyncio/services/intel.py
pangea/asyncio/services/prompt_guard.py
pangea/asyncio/services/redact.py
pangea/asyncio/services/sanitize.py
pangea/asyncio/services/share.py
pangea/asyncio/services/vault.py
pangea/audit_logger.py
pangea/config.py
pangea/crypto/rsa.py
pangea/deep_verify.py
pangea/deprecated.py
pangea/dump_audit.py
pangea/exceptions.py
pangea/file_uploader.py
pangea/py.typed
pangea/request.py
pangea/response.py
pangea/services/__init__.py
pangea/services/ai_guard.py
pangea/services/audit/audit.py
pangea/services/audit/exceptions.py
pangea/services/audit/models.py
pangea/services/audit/signing.py
pangea/services/audit/util.py
pangea/services/authn/authn.py
pangea/services/authn/models.py
pangea/services/authz.py
pangea/services/base.py
pangea/services/embargo.py
pangea/services/file_scan.py
pangea/services/intel.py
pangea/services/prompt_guard.py
pangea/services/redact.py
pangea/services/sanitize.py
pangea/services/share/file_format.py
pangea/services/share/share.py
pangea/services/vault/models/asymmetric.py
pangea/services/vault/models/common.py
pangea/services/vault/models/keys.py
pangea/services/vault/models/secret.py
pangea/services/vault/models/symmetric.py
pangea/services/vault/vault.py
pangea/tools.py
pangea/utils.py
pangea/verify_audit.py
pangea_sdk-6.13.0.dist-info/WHEEL
pangea_sdk-6.13.0.dist-info/METADATA
pangea_sdk-6.13.0.dist-info/RECORD
