Metadata-Version: 2.4
Name: pangea-sdk
Version: 6.13.0
Summary: Pangea API SDK
Keywords: Pangea,SDK,Audit
Author: Glenn Gallien
Author-email: Glenn Gallien <glenn.gallien@pangea.cloud>
License-Expression: MIT
Classifier: Topic :: Software Development
Classifier: Topic :: Software Development :: Libraries
Requires-Dist: aiohttp>=3.13.2,<4.0.0
Requires-Dist: cryptography>=46.0.3,<47.0.0
Requires-Dist: deprecated>=1.3.1,<2.0.0
Requires-Dist: google-crc32c>=1.7.1,<2.0.0
Requires-Dist: pydantic>=2.12.4,<3.0.0
Requires-Dist: python-dateutil>=2.9.0.post0,<3.0.0
Requires-Dist: requests>=2.32.5,<3.0.0
Requires-Dist: requests-toolbelt>=1.0.0,<2.0.0
Requires-Dist: typing-extensions>=4.15.0,<5.0.0
Requires-Dist: yarl>=1.22.0,<2.0.0
Requires-Python: >=3.9.2, <4.0.0
Project-URL: repository, https://github.com/pangeacyber/pangea-python
